[
    {
        "emp_id": "4ebb6ba8-8296-4dd7-bc85-a9dc5778584a",
        "emp_name": "aaaa",
        "age": "aaaa",
        "city": "aaaa",
        "experience": "aaaa"
    },
    {
        "emp_id": "2745b714-e948-4e5b-8b6b-3af1db8e4492",
        "emp_name": "baby",
        "age": "23",
        "city": "bbsr",
        "experience": "2"
    },
    {
        "emp_id": "07791def-5d87-4c51-9606-4d75ce92281a",
        "emp_name": "nitesh kamal",
        "age": "23",
        "city": "bbsr",
        "experience": "2"
    }
]